TweetCatcherPy/__init__.py
TweetCatcherPy/main.py
TweetCatcherPy/test.py
TweetCatcherPy-0.0.7.dist-info/LICENCE.md
TweetCatcherPy-0.0.7.dist-info/METADATA
TweetCatcherPy-0.0.7.dist-info/WHEEL
TweetCatcherPy-0.0.7.dist-info/top_level.txt
TweetCatcherPy-0.0.7.dist-info/RECORD
