Metadata-Version: 2.2
Name: TweetCatcherPy
Version: 0.0.7
Summary: Tweet Catcher API Python Wrapper
Author-email: LnsTchTps <lns@tchtped.me>
Project-URL: Homepage, https://github.com/lnstchtped/TweetCatcherPy
Classifier: Programming Language :: Python :: 3
Classifier: Programming Language :: Python :: 3.11
Classifier: Operating System :: OS Independent
Classifier: License :: Other/Proprietary License
Requires-Python: >=3.11
License-File: LICENCE.md
Requires-Dist: httpx>=0.20.0
Requires-Dist: websockets>=10.0
